{
  "a_comp_cor_00": {
    "CumulativeVarianceExplained": 0.0334337662,
    "Mask": "combined",
    "Method": "aCompCor",
    "Retained": true,
    "SingularValue": 124.2329622418,
    "VarianceExplained": 0.0334337662
  },
  "a_comp_cor_01": {
    "CumulativeVarianceExplained": 0.0544133949,
    "Mask": "combined",
    "Method": "aCompCor",
    "Retained": true,
    "SingularValue": 98.4108737771,
    "VarianceExplained": 0.0209796286
  },
  "a_comp_cor_02": {
    "CumulativeVarianceExplained": 0.0703783361,
    "Mask": "combined",
    "Method": "aCompCor",
    "Retained": true,
    "SingularValue": 85.8475395969,
    "VarianceExplained": 0.0159649413
  },
  "a_comp_cor_03": {
    "CumulativeVarianceExplained": 0.0846254186,
    "Mask": "combined",
    "Method": "aCompCor",
    "Retained": true,
    "SingularValue": 81.0974424724,
    "VarianceExplained": 0.0142470824
  },
  "a_comp_cor_04": {
    "CumulativeVarianceExplained": 0.0964823356,
    "Mask": "combined",
    "Method": "aCompCor",
    "Retained": true,
    "SingularValue": 73.9826837234,
    "VarianceExplained": 0.0118569171
  },
  "a_comp_cor_05": {
    "CumulativeVarianceExplained": 0.1069484746,
    "Mask": "combined",
    "Method": "aCompCor",
    "Retained": true,
    "SingularValue": 69.508423574,
    "VarianceExplained": 0.010466139
  },
  "a_comp_cor_06": {
    "CumulativeVarianceExplained": 0.1172411648,
    "Mask": "combined",
    "Method": "aCompCor",
    "Retained": true,
    "SingularValue": 68.9300572578,
    "VarianceExplained": 0.0102926901
  },
  "a_comp_cor_07": {
    "CumulativeVarianceExplained": 0.1273825368,
    "Mask": "combined",
    "Method": "aCompCor",
    "Retained": true,
    "SingularValue": 68.4214930517,
    "VarianceExplained": 0.010141372
  },
  "a_comp_cor_08": {
    "CumulativeVarianceExplained": 0.1374274848,
    "Mask": "combined",
    "Method": "aCompCor",
    "Retained": true,
    "SingularValue": 68.0954409917,
    "VarianceExplained": 0.010044948
  },
  "a_comp_cor_09": {
    "CumulativeVarianceExplained": 0.147275143,
    "Mask": "combined",
    "Method": "aCompCor",
    "Retained": true,
    "SingularValue": 67.4234036818,
    "VarianceExplained": 0.0098476582
  },
  "a_comp_cor_10": {
    "CumulativeVarianceExplained": 0.1568652177,
    "Mask": "combined",
    "Method": "aCompCor",
    "Retained": true,
    "SingularValue": 66.5357695672,
    "VarianceExplained": 0.0095900747
  },
  "a_comp_cor_11": {
    "CumulativeVarianceExplained": 0.1661871277,
    "Mask": "combined",
    "Method": "aCompCor",
    "Retained": true,
    "SingularValue": 65.5989131024,
    "VarianceExplained": 0.00932191
  },
  "a_comp_cor_12": {
    "CumulativeVarianceExplained": 0.1754442969,
    "Mask": "combined",
    "Method": "aCompCor",
    "Retained": true,
    "SingularValue": 65.3707232887,
    "VarianceExplained": 0.0092571692
  },
  "a_comp_cor_13": {
    "CumulativeVarianceExplained": 0.184411888,
    "Mask": "combined",
    "Method": "aCompCor",
    "Retained": true,
    "SingularValue": 64.3401530996,
    "VarianceExplained": 0.0089675912
  },
  "a_comp_cor_14": {
    "CumulativeVarianceExplained": 0.193355077,
    "Mask": "combined",
    "Method": "aCompCor",
    "Retained": true,
    "SingularValue": 64.2525536507,
    "VarianceExplained": 0.0089431889
  },
  "a_comp_cor_15": {
    "CumulativeVarianceExplained": 0.2022590753,
    "Mask": "combined",
    "Method": "aCompCor",
    "Retained": true,
    "SingularValue": 64.1116161357,
    "VarianceExplained": 0.0089039983
  },
  "a_comp_cor_16": {
    "CumulativeVarianceExplained": 0.2110069807,
    "Mask": "combined",
    "Method": "aCompCor",
    "Retained": true,
    "SingularValue": 63.5471722685,
    "VarianceExplained": 0.0087479054
  },
  "a_comp_cor_17": {
    "CumulativeVarianceExplained": 0.2196680766,
    "Mask": "combined",
    "Method": "aCompCor",
    "Retained": true,
    "SingularValue": 63.2310818552,
    "VarianceExplained": 0.0086610959
  },
  "a_comp_cor_18": {
    "CumulativeVarianceExplained": 0.2283049318,
    "Mask": "combined",
    "Method": "aCompCor",
    "Retained": true,
    "SingularValue": 63.1425344496,
    "VarianceExplained": 0.0086368552
  },
  "a_comp_cor_19": {
    "CumulativeVarianceExplained": 0.2368329874,
    "Mask": "combined",
    "Method": "aCompCor",
    "Retained": true,
    "SingularValue": 62.7435664257,
    "VarianceExplained": 0.0085280556
  },
  "a_comp_cor_20": {
    "CumulativeVarianceExplained": 0.2452851521,
    "Mask": "combined",
    "Method": "aCompCor",
    "Retained": true,
    "SingularValue": 62.4637662173,
    "VarianceExplained": 0.0084521647
  },
  "a_comp_cor_21": {
    "CumulativeVarianceExplained": 0.2537097925,
    "Mask": "combined",
    "Method": "aCompCor",
    "Retained": true,
    "SingularValue": 62.3619770705,
    "VarianceExplained": 0.0084246404
  },
  "a_comp_cor_22": {
    "CumulativeVarianceExplained": 0.2620692529,
    "Mask": "combined",
    "Method": "aCompCor",
    "Retained": true,
    "SingularValue": 62.120266876,
    "VarianceExplained": 0.0083594604
  },
  "a_comp_cor_23": {
    "CumulativeVarianceExplained": 0.2703529316,
    "Mask": "combined",
    "Method": "aCompCor",
    "Retained": true,
    "SingularValue": 61.8380536591,
    "VarianceExplained": 0.0082836787
  },
  "a_comp_cor_24": {
    "CumulativeVarianceExplained": 0.2785289728,
    "Mask": "combined",
    "Method": "aCompCor",
    "Retained": true,
    "SingularValue": 61.4349806535,
    "VarianceExplained": 0.0081760412
  },
  "a_comp_cor_25": {
    "CumulativeVarianceExplained": 0.2866591393,
    "Mask": "combined",
    "Method": "aCompCor",
    "Retained": true,
    "SingularValue": 61.2623862974,
    "VarianceExplained": 0.0081301665
  },
  "a_comp_cor_26": {
    "CumulativeVarianceExplained": 0.2947778695,
    "Mask": "combined",
    "Method": "aCompCor",
    "Retained": true,
    "SingularValue": 61.2192838356,
    "VarianceExplained": 0.0081187302
  },
  "a_comp_cor_27": {
    "CumulativeVarianceExplained": 0.302831045,
    "Mask": "combined",
    "Method": "aCompCor",
    "Retained": true,
    "SingularValue": 60.9716252636,
    "VarianceExplained": 0.0080531755
  },
  "a_comp_cor_28": {
    "CumulativeVarianceExplained": 0.310862701,
    "Mask": "combined",
    "Method": "aCompCor",
    "Retained": true,
    "SingularValue": 60.8901074518,
    "VarianceExplained": 0.008031656
  },
  "a_comp_cor_29": {
    "CumulativeVarianceExplained": 0.3188485602,
    "Mask": "combined",
    "Method": "aCompCor",
    "Retained": true,
    "SingularValue": 60.7162600929,
    "VarianceExplained": 0.0079858591
  },
  "a_comp_cor_30": {
    "CumulativeVarianceExplained": 0.3268219744,
    "Mask": "combined",
    "Method": "aCompCor",
    "Retained": true,
    "SingularValue": 60.6689325094,
    "VarianceExplained": 0.0079734142
  },
  "a_comp_cor_31": {
    "CumulativeVarianceExplained": 0.3347357677,
    "Mask": "combined",
    "Method": "aCompCor",
    "Retained": true,
    "SingularValue": 60.4416817797,
    "VarianceExplained": 0.0079137933
  },
  "a_comp_cor_32": {
    "CumulativeVarianceExplained": 0.3425525979,
    "Mask": "combined",
    "Method": "aCompCor",
    "Retained": true,
    "SingularValue": 60.0702627105,
    "VarianceExplained": 0.0078168303
  },
  "a_comp_cor_33": {
    "CumulativeVarianceExplained": 0.3503234143,
    "Mask": "combined",
    "Method": "aCompCor",
    "Retained": true,
    "SingularValue": 59.8931994262,
    "VarianceExplained": 0.0077708164
  },
  "a_comp_cor_34": {
    "CumulativeVarianceExplained": 0.358033075,
    "Mask": "combined",
    "Method": "aCompCor",
    "Retained": true,
    "SingularValue": 59.6570566166,
    "VarianceExplained": 0.0077096607
  },
  "a_comp_cor_35": {
    "CumulativeVarianceExplained": 0.365723859,
    "Mask": "combined",
    "Method": "aCompCor",
    "Retained": true,
    "SingularValue": 59.5839783707,
    "VarianceExplained": 0.007690784
  },
  "a_comp_cor_36": {
    "CumulativeVarianceExplained": 0.3733564328,
    "Mask": "combined",
    "Method": "aCompCor",
    "Retained": true,
    "SingularValue": 59.3580595087,
    "VarianceExplained": 0.0076325738
  },
  "a_comp_cor_37": {
    "CumulativeVarianceExplained": 0.3809262394,
    "Mask": "combined",
    "Method": "aCompCor",
    "Retained": true,
    "SingularValue": 59.1134876866,
    "VarianceExplained": 0.0075698067
  },
  "a_comp_cor_38": {
    "CumulativeVarianceExplained": 0.3884238257,
    "Mask": "combined",
    "Method": "aCompCor",
    "Retained": true,
    "SingularValue": 58.8308232676,
    "VarianceExplained": 0.0074975863
  },
  "a_comp_cor_39": {
    "CumulativeVarianceExplained": 0.3959044443,
    "Mask": "combined",
    "Method": "aCompCor",
    "Retained": true,
    "SingularValue": 58.7642158396,
    "VarianceExplained": 0.0074806186
  },
  "a_comp_cor_40": {
    "CumulativeVarianceExplained": 0.4033754693,
    "Mask": "combined",
    "Method": "aCompCor",
    "Retained": true,
    "SingularValue": 58.7265225017,
    "VarianceExplained": 0.007471025
  },
  "a_comp_cor_41": {
    "CumulativeVarianceExplained": 0.4107849332,
    "Mask": "combined",
    "Method": "aCompCor",
    "Retained": true,
    "SingularValue": 58.4840693566,
    "VarianceExplained": 0.0074094639
  },
  "a_comp_cor_42": {
    "CumulativeVarianceExplained": 0.4181187225,
    "Mask": "combined",
    "Method": "aCompCor",
    "Retained": true,
    "SingularValue": 58.1846470112,
    "VarianceExplained": 0.0073337893
  },
  "a_comp_cor_43": {
    "CumulativeVarianceExplained": 0.4254154638,
    "Mask": "combined",
    "Method": "aCompCor",
    "Retained": true,
    "SingularValue": 58.0374957352,
    "VarianceExplained": 0.0072967413
  },
  "a_comp_cor_44": {
    "CumulativeVarianceExplained": 0.4326342144,
    "Mask": "combined",
    "Method": "aCompCor",
    "Retained": true,
    "SingularValue": 57.7264977895,
    "VarianceExplained": 0.0072187506
  },
  "a_comp_cor_45": {
    "CumulativeVarianceExplained": 0.4398215941,
    "Mask": "combined",
    "Method": "aCompCor",
    "Retained": true,
    "SingularValue": 57.6009284528,
    "VarianceExplained": 0.0071873797
  },
  "a_comp_cor_46": {
    "CumulativeVarianceExplained": 0.4469670871,
    "Mask": "combined",
    "Method": "aCompCor",
    "Retained": true,
    "SingularValue": 57.4328395346,
    "VarianceExplained": 0.007145493
  },
  "a_comp_cor_47": {
    "CumulativeVarianceExplained": 0.454086789,
    "Mask": "combined",
    "Method": "aCompCor",
    "Retained": true,
    "SingularValue": 57.3290964306,
    "VarianceExplained": 0.007119702
  },
  "a_comp_cor_48": {
    "CumulativeVarianceExplained": 0.4611750871,
    "Mask": "combined",
    "Method": "aCompCor",
    "Retained": true,
    "SingularValue": 57.202521618,
    "VarianceExplained": 0.007088298
  },
  "a_comp_cor_49": {
    "CumulativeVarianceExplained": 0.4682566298,
    "Mask": "combined",
    "Method": "aCompCor",
    "Retained": true,
    "SingularValue": 57.1752577947,
    "VarianceExplained": 0.0070815428
  },
  "a_comp_cor_50": {
    "CumulativeVarianceExplained": 0.4752878795,
    "Mask": "combined",
    "Method": "aCompCor",
    "Retained": true,
    "SingularValue": 56.9718667696,
    "VarianceExplained": 0.0070312497
  },
  "a_comp_cor_51": {
    "CumulativeVarianceExplained": 0.4822986177,
    "Mask": "combined",
    "Method": "aCompCor",
    "Retained": true,
    "SingularValue": 56.8887070378,
    "VarianceExplained": 0.0070107382
  },
  "a_comp_cor_52": {
    "CumulativeVarianceExplained": 0.4893025791,
    "Mask": "combined",
    "Method": "aCompCor",
    "Retained": true,
    "SingularValue": 56.8612053814,
    "VarianceExplained": 0.0070039614
  },
  "a_comp_cor_53": {
    "CumulativeVarianceExplained": 0.496199459,
    "Mask": "combined",
    "Method": "aCompCor",
    "Retained": true,
    "SingularValue": 56.4248642063,
    "VarianceExplained": 0.0068968799
  },
  "a_comp_cor_54": {
    "CumulativeVarianceExplained": 0.5030502969,
    "Mask": "combined",
    "Method": "aCompCor",
    "Retained": true,
    "SingularValue": 56.2362090103,
    "VarianceExplained": 0.0068508379
  },
  "c_comp_cor_00": {
    "CumulativeVarianceExplained": 0.0925285252,
    "Mask": "CSF",
    "Method": "aCompCor",
    "Retained": true,
    "SingularValue": 63.754161094,
    "VarianceExplained": 0.0925285252
  },
  "c_comp_cor_01": {
    "CumulativeVarianceExplained": 0.1659456134,
    "Mask": "CSF",
    "Method": "aCompCor",
    "Retained": true,
    "SingularValue": 56.7896632256,
    "VarianceExplained": 0.0734170882
  },
  "c_comp_cor_02": {
    "CumulativeVarianceExplained": 0.2196761299,
    "Mask": "CSF",
    "Method": "aCompCor",
    "Retained": true,
    "SingularValue": 48.5826525227,
    "VarianceExplained": 0.0537305164
  },
  "c_comp_cor_03": {
    "CumulativeVarianceExplained": 0.2685678059,
    "Mask": "CSF",
    "Method": "aCompCor",
    "Retained": true,
    "SingularValue": 46.3434304554,
    "VarianceExplained": 0.0488916761
  },
  "c_comp_cor_04": {
    "CumulativeVarianceExplained": 0.3155730358,
    "Mask": "CSF",
    "Method": "aCompCor",
    "Retained": true,
    "SingularValue": 45.4405736809,
    "VarianceExplained": 0.0470052298
  },
  "c_comp_cor_05": {
    "CumulativeVarianceExplained": 0.3500605949,
    "Mask": "CSF",
    "Method": "aCompCor",
    "Retained": true,
    "SingularValue": 38.9226090925,
    "VarianceExplained": 0.0344875592
  },
  "c_comp_cor_06": {
    "CumulativeVarianceExplained": 0.3813226909,
    "Mask": "CSF",
    "Method": "aCompCor",
    "Retained": true,
    "SingularValue": 37.0578109723,
    "VarianceExplained": 0.031262096
  },
  "c_comp_cor_07": {
    "CumulativeVarianceExplained": 0.4116795899,
    "Mask": "CSF",
    "Method": "aCompCor",
    "Retained": true,
    "SingularValue": 36.5173637734,
    "VarianceExplained": 0.0303568989
  },
  "c_comp_cor_08": {
    "CumulativeVarianceExplained": 0.4379571297,
    "Mask": "CSF",
    "Method": "aCompCor",
    "Retained": true,
    "SingularValue": 33.9752817234,
    "VarianceExplained": 0.0262775398
  },
  "c_comp_cor_09": {
    "CumulativeVarianceExplained": 0.4598139541,
    "Mask": "CSF",
    "Method": "aCompCor",
    "Retained": true,
    "SingularValue": 30.9859094258,
    "VarianceExplained": 0.0218568244
  },
  "c_comp_cor_10": {
    "CumulativeVarianceExplained": 0.4800784119,
    "Mask": "CSF",
    "Method": "aCompCor",
    "Retained": true,
    "SingularValue": 29.8358358466,
    "VarianceExplained": 0.0202644578
  },
  "c_comp_cor_11": {
    "CumulativeVarianceExplained": 0.4986449162,
    "Mask": "CSF",
    "Method": "aCompCor",
    "Retained": true,
    "SingularValue": 28.558525946,
    "VarianceExplained": 0.0185665044
  },
  "c_comp_cor_12": {
    "CumulativeVarianceExplained": 0.5151593036,
    "Mask": "CSF",
    "Method": "aCompCor",
    "Retained": true,
    "SingularValue": 26.9340677611,
    "VarianceExplained": 0.0165143873
  },
  "dropped_0": {
    "CumulativeVarianceExplained": 0.3154473485,
    "Mask": "Edge",
    "Method": "EdgeRegressor",
    "Retained": false,
    "SingularValue": 121.6334944578,
    "VarianceExplained": 0.007071607
  },
  "dropped_1": {
    "CumulativeVarianceExplained": 0.3224312467,
    "Mask": "Edge",
    "Method": "EdgeRegressor",
    "Retained": false,
    "SingularValue": 120.8768342887,
    "VarianceExplained": 0.0069838982
  },
  "dropped_10": {
    "CumulativeVarianceExplained": 0.3834607441,
    "Mask": "Edge",
    "Method": "EdgeRegressor",
    "Retained": false,
    "SingularValue": 117.9765805829,
    "VarianceExplained": 0.006652783
  },
  "dropped_100": {
    "CumulativeVarianceExplained": 0.8938733071,
    "Mask": "Edge",
    "Method": "EdgeRegressor",
    "Retained": false,
    "SingularValue": 101.5333512744,
    "VarianceExplained": 0.004927529
  },
  "dropped_101": {
    "CumulativeVarianceExplained": 0.8987951159,
    "Mask": "Edge",
    "Method": "EdgeRegressor",
    "Retained": false,
    "SingularValue": 101.4744006178,
    "VarianceExplained": 0.0049218088
  },
  "dropped_102": {
    "CumulativeVarianceExplained": 0.9037038577,
    "Mask": "Edge",
    "Method": "EdgeRegressor",
    "Retained": false,
    "SingularValue": 101.3396084783,
    "VarianceExplained": 0.0049087418
  },
  "dropped_103": {
    "CumulativeVarianceExplained": 0.9085980429,
    "Mask": "Edge",
    "Method": "EdgeRegressor",
    "Retained": false,
    "SingularValue": 101.1892382021,
    "VarianceExplained": 0.0048941852
  },
  "dropped_104": {
    "CumulativeVarianceExplained": 0.9134641524,
    "Mask": "Edge",
    "Method": "EdgeRegressor",
    "Retained": false,
    "SingularValue": 100.8985818161,
    "VarianceExplained": 0.0048661094
  },
  "dropped_105": {
    "CumulativeVarianceExplained": 0.9183224805,
    "Mask": "Edge",
    "Method": "EdgeRegressor",
    "Retained": false,
    "SingularValue": 100.8178769046,
    "VarianceExplained": 0.0048583281
  },
  "dropped_106": {
    "CumulativeVarianceExplained": 0.9231791534,
    "Mask": "Edge",
    "Method": "EdgeRegressor",
    "Retained": false,
    "SingularValue": 100.8007010888,
    "VarianceExplained": 0.0048566729
  },
  "dropped_107": {
    "CumulativeVarianceExplained": 0.9280080206,
    "Mask": "Edge",
    "Method": "EdgeRegressor",
    "Retained": false,
    "SingularValue": 100.5117326022,
    "VarianceExplained": 0.0048288673
  },
  "dropped_108": {
    "CumulativeVarianceExplained": 0.9328139957,
    "Mask": "Edge",
    "Method": "EdgeRegressor",
    "Retained": false,
    "SingularValue": 100.2732014873,
    "VarianceExplained": 0.004805975
  },
  "dropped_109": {
    "CumulativeVarianceExplained": 0.9376149045,
    "Mask": "Edge",
    "Method": "EdgeRegressor",
    "Retained": false,
    "SingularValue": 100.2203366763,
    "VarianceExplained": 0.0048009089
  },
  "dropped_11": {
    "CumulativeVarianceExplained": 0.3900524379,
    "Mask": "Edge",
    "Method": "EdgeRegressor",
    "Retained": false,
    "SingularValue": 117.4336708908,
    "VarianceExplained": 0.0065916937
  },
  "dropped_110": {
    "CumulativeVarianceExplained": 0.9423743146,
    "Mask": "Edge",
    "Method": "EdgeRegressor",
    "Retained": false,
    "SingularValue": 99.7862464085,
    "VarianceExplained": 0.00475941
  },
  "dropped_111": {
    "CumulativeVarianceExplained": 0.9471303204,
    "Mask": "Edge",
    "Method": "EdgeRegressor",
    "Retained": false,
    "SingularValue": 99.7505541999,
    "VarianceExplained": 0.0047560059
  },
  "dropped_112": {
    "CumulativeVarianceExplained": 0.9518275771,
    "Mask": "Edge",
    "Method": "EdgeRegressor",
    "Retained": false,
    "SingularValue": 99.1325480992,
    "VarianceExplained": 0.0046972566
  },
  "dropped_113": {
    "CumulativeVarianceExplained": 0.9565209377,
    "Mask": "Edge",
    "Method": "EdgeRegressor",
    "Retained": false,
    "SingularValue": 99.0914280902,
    "VarianceExplained": 0.0046933606
  },
  "dropped_114": {
    "CumulativeVarianceExplained": 0.9611908386,
    "Mask": "Edge",
    "Method": "EdgeRegressor",
    "Retained": false,
    "SingularValue": 98.8434641623,
    "VarianceExplained": 0.0046699009
  },
  "dropped_115": {
    "CumulativeVarianceExplained": 0.9658313974,
    "Mask": "Edge",
    "Method": "EdgeRegressor",
    "Retained": false,
    "SingularValue": 98.532446716,
    "VarianceExplained": 0.0046405588
  },
  "dropped_116": {
    "CumulativeVarianceExplained": 0.9704686966,
    "Mask": "Edge",
    "Method": "EdgeRegressor",
    "Retained": false,
    "SingularValue": 98.4978356826,
    "VarianceExplained": 0.0046372993
  },
  "dropped_117": {
    "CumulativeVarianceExplained": 0.975078488,
    "Mask": "Edge",
    "Method": "EdgeRegressor",
    "Retained": false,
    "SingularValue": 98.2052629667,
    "VarianceExplained": 0.0046097914
  },
  "dropped_118": {
    "CumulativeVarianceExplained": 0.9796687039,
    "Mask": "Edge",
    "Method": "EdgeRegressor",
    "Retained": false,
    "SingularValue": 97.9965263589,
    "VarianceExplained": 0.0045902159
  },
  "dropped_119": {
    "CumulativeVarianceExplained": 0.9842503449,
    "Mask": "Edge",
    "Method": "EdgeRegressor",
    "Retained": false,
    "SingularValue": 97.9049510948,
    "VarianceExplained": 0.004581641
  },
  "dropped_12": {
    "CumulativeVarianceExplained": 0.396607278,
    "Mask": "Edge",
    "Method": "EdgeRegressor",
    "Retained": false,
    "SingularValue": 117.1049292153,
    "VarianceExplained": 0.0065548401
  },
  "dropped_120": {
    "CumulativeVarianceExplained": 0.9887847153,
    "Mask": "Edge",
    "Method": "EdgeRegressor",
    "Retained": false,
    "SingularValue": 97.3985792753,
    "VarianceExplained": 0.0045343704
  },
  "dropped_121": {
    "CumulativeVarianceExplained": 0.9932395017,
    "Mask": "Edge",
    "Method": "EdgeRegressor",
    "Retained": false,
    "SingularValue": 96.5400604151,
    "VarianceExplained": 0.0044547864
  },
  "dropped_122": {
    "CumulativeVarianceExplained": 0.9971690656,
    "Mask": "Edge",
    "Method": "EdgeRegressor",
    "Retained": false,
    "SingularValue": 90.6705609441,
    "VarianceExplained": 0.0039295639
  },
  "dropped_123": {
    "CumulativeVarianceExplained": 1.0,
    "Mask": "Edge",
    "Method": "EdgeRegressor",
    "Retained": false,
    "SingularValue": 76.9589318824,
    "VarianceExplained": 0.0028309344
  },
  "dropped_124": {
    "CumulativeVarianceExplained": 1.0,
    "Mask": "Edge",
    "Method": "EdgeRegressor",
    "Retained": false,
    "SingularValue": 0.0,
    "VarianceExplained": 0.0
  },
  "dropped_125": {
    "CumulativeVarianceExplained": 1.0,
    "Mask": "Edge",
    "Method": "EdgeRegressor",
    "Retained": false,
    "SingularValue": 0.0,
    "VarianceExplained": 0.0
  },
  "dropped_126": {
    "CumulativeVarianceExplained": 1.0,
    "Mask": "Edge",
    "Method": "EdgeRegressor",
    "Retained": false,
    "SingularValue": 0.0,
    "VarianceExplained": 0.0
  },
  "dropped_127": {
    "CumulativeVarianceExplained": 1.0,
    "Mask": "Edge",
    "Method": "EdgeRegressor",
    "Retained": false,
    "SingularValue": 0.0,
    "VarianceExplained": 0.0
  },
  "dropped_13": {
    "CumulativeVarianceExplained": 0.4031053345,
    "Mask": "Edge",
    "Method": "EdgeRegressor",
    "Retained": false,
    "SingularValue": 116.5965950393,
    "VarianceExplained": 0.0064980565
  },
  "dropped_14": {
    "CumulativeVarianceExplained": 0.4095797228,
    "Mask": "Edge",
    "Method": "EdgeRegressor",
    "Retained": false,
    "SingularValue": 116.3840583294,
    "VarianceExplained": 0.0064743883
  },
  "dropped_15": {
    "CumulativeVarianceExplained": 0.4160394829,
    "Mask": "Edge",
    "Method": "EdgeRegressor",
    "Retained": false,
    "SingularValue": 116.2525057229,
    "VarianceExplained": 0.0064597602
  },
  "dropped_16": {
    "CumulativeVarianceExplained": 0.4224638116,
    "Mask": "Edge",
    "Method": "EdgeRegressor",
    "Retained": false,
    "SingularValue": 115.9332479131,
    "VarianceExplained": 0.0064243287
  },
  "dropped_17": {
    "CumulativeVarianceExplained": 0.42884778,
    "Mask": "Edge",
    "Method": "EdgeRegressor",
    "Retained": false,
    "SingularValue": 115.5685035274,
    "VarianceExplained": 0.0063839684
  },
  "dropped_18": {
    "CumulativeVarianceExplained": 0.4351968539,
    "Mask": "Edge",
    "Method": "EdgeRegressor",
    "Retained": false,
    "SingularValue": 115.2522241861,
    "VarianceExplained": 0.0063490739
  },
  "dropped_19": {
    "CumulativeVarianceExplained": 0.4415433373,
    "Mask": "Edge",
    "Method": "EdgeRegressor",
    "Retained": false,
    "SingularValue": 115.228710208,
    "VarianceExplained": 0.0063464834
  },
  "dropped_2": {
    "CumulativeVarianceExplained": 0.329342503,
    "Mask": "Edge",
    "Method": "EdgeRegressor",
    "Retained": false,
    "SingularValue": 120.2465499979,
    "VarianceExplained": 0.0069112563
  },
  "dropped_20": {
    "CumulativeVarianceExplained": 0.4478706166,
    "Mask": "Edge",
    "Method": "EdgeRegressor",
    "Retained": false,
    "SingularValue": 115.0542399247,
    "VarianceExplained": 0.0063272793
  },
  "dropped_21": {
    "CumulativeVarianceExplained": 0.4541531798,
    "Mask": "Edge",
    "Method": "EdgeRegressor",
    "Retained": false,
    "SingularValue": 114.6469646392,
    "VarianceExplained": 0.0062825633
  },
  "dropped_22": {
    "CumulativeVarianceExplained": 0.4604229219,
    "Mask": "Edge",
    "Method": "EdgeRegressor",
    "Retained": false,
    "SingularValue": 114.5299217898,
    "VarianceExplained": 0.0062697421
  },
  "dropped_23": {
    "CumulativeVarianceExplained": 0.466653906,
    "Mask": "Edge",
    "Method": "EdgeRegressor",
    "Retained": false,
    "SingularValue": 114.1753756305,
    "VarianceExplained": 0.0062309841
  },
  "dropped_24": {
    "CumulativeVarianceExplained": 0.4728771652,
    "Mask": "Edge",
    "Method": "EdgeRegressor",
    "Retained": false,
    "SingularValue": 114.1045783613,
    "VarianceExplained": 0.0062232592
  },
  "dropped_25": {
    "CumulativeVarianceExplained": 0.4790849914,
    "Mask": "Edge",
    "Method": "EdgeRegressor",
    "Retained": false,
    "SingularValue": 113.9630065235,
    "VarianceExplained": 0.0062078261
  },
  "dropped_26": {
    "CumulativeVarianceExplained": 0.4852572762,
    "Mask": "Edge",
    "Method": "EdgeRegressor",
    "Retained": false,
    "SingularValue": 113.6363056091,
    "VarianceExplained": 0.0061722848
  },
  "dropped_27": {
    "CumulativeVarianceExplained": 0.491412314,
    "Mask": "Edge",
    "Method": "EdgeRegressor",
    "Retained": false,
    "SingularValue": 113.4774294153,
    "VarianceExplained": 0.0061550378
  },
  "dropped_28": {
    "CumulativeVarianceExplained": 0.4975511309,
    "Mask": "Edge",
    "Method": "EdgeRegressor",
    "Retained": false,
    "SingularValue": 113.3278013785,
    "VarianceExplained": 0.0061388168
  },
  "dropped_29": {
    "CumulativeVarianceExplained": 0.5036691677,
    "Mask": "Edge",
    "Method": "EdgeRegressor",
    "Retained": false,
    "SingularValue": 113.1358306355,
    "VarianceExplained": 0.0061180368
  },
  "dropped_3": {
    "CumulativeVarianceExplained": 0.3362240854,
    "Mask": "Edge",
    "Method": "EdgeRegressor",
    "Retained": false,
    "SingularValue": 119.9881297939,
    "VarianceExplained": 0.0068815824
  },
  "dropped_30": {
    "CumulativeVarianceExplained": 0.5097716046,
    "Mask": "Edge",
    "Method": "EdgeRegressor",
    "Retained": false,
    "SingularValue": 112.9914997677,
    "VarianceExplained": 0.0061024369
  },
  "dropped_31": {
    "CumulativeVarianceExplained": 0.5158493651,
    "Mask": "Edge",
    "Method": "EdgeRegressor",
    "Retained": false,
    "SingularValue": 112.7628176256,
    "VarianceExplained": 0.0060777606
  },
  "dropped_32": {
    "CumulativeVarianceExplained": 0.5218990699,
    "Mask": "Edge",
    "Method": "EdgeRegressor",
    "Retained": false,
    "SingularValue": 112.5022524527,
    "VarianceExplained": 0.0060497048
  },
  "dropped_33": {
    "CumulativeVarianceExplained": 0.5279394057,
    "Mask": "Edge",
    "Method": "EdgeRegressor",
    "Retained": false,
    "SingularValue": 112.4151038926,
    "VarianceExplained": 0.0060403358
  },
  "dropped_34": {
    "CumulativeVarianceExplained": 0.5339589531,
    "Mask": "Edge",
    "Method": "EdgeRegressor",
    "Retained": false,
    "SingularValue": 112.2214936786,
    "VarianceExplained": 0.0060195474
  },
  "dropped_35": {
    "CumulativeVarianceExplained": 0.5399706569,
    "Mask": "Edge",
    "Method": "EdgeRegressor",
    "Retained": false,
    "SingularValue": 112.1483570365,
    "VarianceExplained": 0.0060117039
  },
  "dropped_36": {
    "CumulativeVarianceExplained": 0.5459539453,
    "Mask": "Edge",
    "Method": "EdgeRegressor",
    "Retained": false,
    "SingularValue": 111.8829974228,
    "VarianceExplained": 0.0059832884
  },
  "dropped_37": {
    "CumulativeVarianceExplained": 0.5519108167,
    "Mask": "Edge",
    "Method": "EdgeRegressor",
    "Retained": false,
    "SingularValue": 111.6357351831,
    "VarianceExplained": 0.0059568714
  },
  "dropped_38": {
    "CumulativeVarianceExplained": 0.5578650015,
    "Mask": "Edge",
    "Method": "EdgeRegressor",
    "Retained": false,
    "SingularValue": 111.6105591445,
    "VarianceExplained": 0.0059541849
  },
  "dropped_39": {
    "CumulativeVarianceExplained": 0.5638114361,
    "Mask": "Edge",
    "Method": "EdgeRegressor",
    "Retained": false,
    "SingularValue": 111.5378961141,
    "VarianceExplained": 0.0059464346
  },
  "dropped_4": {
    "CumulativeVarianceExplained": 0.3430691849,
    "Mask": "Edge",
    "Method": "EdgeRegressor",
    "Retained": false,
    "SingularValue": 119.6696466255,
    "VarianceExplained": 0.0068450995
  },
  "dropped_40": {
    "CumulativeVarianceExplained": 0.5697209891,
    "Mask": "Edge",
    "Method": "EdgeRegressor",
    "Retained": false,
    "SingularValue": 111.1914621771,
    "VarianceExplained": 0.005909553
  },
  "dropped_41": {
    "CumulativeVarianceExplained": 0.5756226885,
    "Mask": "Edge",
    "Method": "EdgeRegressor",
    "Retained": false,
    "SingularValue": 111.1175530265,
    "VarianceExplained": 0.0059016994
  },
  "dropped_42": {
    "CumulativeVarianceExplained": 0.5815017041,
    "Mask": "Edge",
    "Method": "EdgeRegressor",
    "Retained": false,
    "SingularValue": 110.9038008956,
    "VarianceExplained": 0.0058790156
  },
  "dropped_43": {
    "CumulativeVarianceExplained": 0.5873315563,
    "Mask": "Edge",
    "Method": "EdgeRegressor",
    "Retained": false,
    "SingularValue": 110.4391101158,
    "VarianceExplained": 0.0058298522
  },
  "dropped_44": {
    "CumulativeVarianceExplained": 0.5931511792,
    "Mask": "Edge",
    "Method": "EdgeRegressor",
    "Retained": false,
    "SingularValue": 110.3421771216,
    "VarianceExplained": 0.0058196229
  },
  "dropped_45": {
    "CumulativeVarianceExplained": 0.5989623191,
    "Mask": "Edge",
    "Method": "EdgeRegressor",
    "Retained": false,
    "SingularValue": 110.2617274756,
    "VarianceExplained": 0.0058111399
  },
  "dropped_46": {
    "CumulativeVarianceExplained": 0.6047685543,
    "Mask": "Edge",
    "Method": "EdgeRegressor",
    "Retained": false,
    "SingularValue": 110.2151855918,
    "VarianceExplained": 0.0058062352
  },
  "dropped_47": {
    "CumulativeVarianceExplained": 0.6105400025,
    "Mask": "Edge",
    "Method": "EdgeRegressor",
    "Retained": false,
    "SingularValue": 109.8845232524,
    "VarianceExplained": 0.0057714482
  },
  "dropped_48": {
    "CumulativeVarianceExplained": 0.6162904458,
    "Mask": "Edge",
    "Method": "EdgeRegressor",
    "Retained": false,
    "SingularValue": 109.6843810555,
    "VarianceExplained": 0.0057504433
  },
  "dropped_49": {
    "CumulativeVarianceExplained": 0.6220254511,
    "Mask": "Edge",
    "Method": "EdgeRegressor",
    "Retained": false,
    "SingularValue": 109.5370494513,
    "VarianceExplained": 0.0057350053
  },
  "dropped_5": {
    "CumulativeVarianceExplained": 0.349894364,
    "Mask": "Edge",
    "Method": "EdgeRegressor",
    "Retained": false,
    "SingularValue": 119.495389762,
    "VarianceExplained": 0.006825179
  },
  "dropped_50": {
    "CumulativeVarianceExplained": 0.6277471809,
    "Mask": "Edge",
    "Method": "EdgeRegressor",
    "Retained": false,
    "SingularValue": 109.410196308,
    "VarianceExplained": 0.0057217298
  },
  "dropped_51": {
    "CumulativeVarianceExplained": 0.6334566493,
    "Mask": "Edge",
    "Method": "EdgeRegressor",
    "Retained": false,
    "SingularValue": 109.2929035773,
    "VarianceExplained": 0.0057094684
  },
  "dropped_52": {
    "CumulativeVarianceExplained": 0.6391505898,
    "Mask": "Edge",
    "Method": "EdgeRegressor",
    "Retained": false,
    "SingularValue": 109.1441811486,
    "VarianceExplained": 0.0056939405
  },
  "dropped_53": {
    "CumulativeVarianceExplained": 0.6448336045,
    "Mask": "Edge",
    "Method": "EdgeRegressor",
    "Retained": false,
    "SingularValue": 109.0394153747,
    "VarianceExplained": 0.0056830147
  },
  "dropped_54": {
    "CumulativeVarianceExplained": 0.6504912942,
    "Mask": "Edge",
    "Method": "EdgeRegressor",
    "Retained": false,
    "SingularValue": 108.7961907684,
    "VarianceExplained": 0.0056576897
  },
  "dropped_55": {
    "CumulativeVarianceExplained": 0.6561337541,
    "Mask": "Edge",
    "Method": "EdgeRegressor",
    "Retained": false,
    "SingularValue": 108.6496589557,
    "VarianceExplained": 0.0056424599
  },
  "dropped_56": {
    "CumulativeVarianceExplained": 0.6617584562,
    "Mask": "Edge",
    "Method": "EdgeRegressor",
    "Retained": false,
    "SingularValue": 108.478553987,
    "VarianceExplained": 0.0056247021
  },
  "dropped_57": {
    "CumulativeVarianceExplained": 0.6673556847,
    "Mask": "Edge",
    "Method": "EdgeRegressor",
    "Retained": false,
    "SingularValue": 108.2133007428,
    "VarianceExplained": 0.0055972285
  },
  "dropped_58": {
    "CumulativeVarianceExplained": 0.6729451281,
    "Mask": "Edge",
    "Method": "EdgeRegressor",
    "Retained": false,
    "SingularValue": 108.1380190324,
    "VarianceExplained": 0.0055894435
  },
  "dropped_59": {
    "CumulativeVarianceExplained": 0.6785173022,
    "Mask": "Edge",
    "Method": "EdgeRegressor",
    "Retained": false,
    "SingularValue": 107.970836155,
    "VarianceExplained": 0.0055721741
  },
  "dropped_6": {
    "CumulativeVarianceExplained": 0.3566803493,
    "Mask": "Edge",
    "Method": "EdgeRegressor",
    "Retained": false,
    "SingularValue": 119.1517936311,
    "VarianceExplained": 0.0067859853
  },
  "dropped_60": {
    "CumulativeVarianceExplained": 0.6840662354,
    "Mask": "Edge",
    "Method": "EdgeRegressor",
    "Retained": false,
    "SingularValue": 107.7454334999,
    "VarianceExplained": 0.0055489332
  },
  "dropped_61": {
    "CumulativeVarianceExplained": 0.6896094583,
    "Mask": "Edge",
    "Method": "EdgeRegressor",
    "Retained": false,
    "SingularValue": 107.6899801403,
    "VarianceExplained": 0.0055432229
  },
  "dropped_62": {
    "CumulativeVarianceExplained": 0.6951289091,
    "Mask": "Edge",
    "Method": "EdgeRegressor",
    "Retained": false,
    "SingularValue": 107.458818487,
    "VarianceExplained": 0.0055194509
  },
  "dropped_63": {
    "CumulativeVarianceExplained": 0.7006425217,
    "Mask": "Edge",
    "Method": "EdgeRegressor",
    "Retained": false,
    "SingularValue": 107.4019703556,
    "VarianceExplained": 0.0055136126
  },
  "dropped_64": {
    "CumulativeVarianceExplained": 0.7061363662,
    "Mask": "Edge",
    "Method": "EdgeRegressor",
    "Retained": false,
    "SingularValue": 107.2092623094,
    "VarianceExplained": 0.0054938445
  },
  "dropped_65": {
    "CumulativeVarianceExplained": 0.711610487,
    "Mask": "Edge",
    "Method": "EdgeRegressor",
    "Retained": false,
    "SingularValue": 107.0166404033,
    "VarianceExplained": 0.0054741208
  },
  "dropped_66": {
    "CumulativeVarianceExplained": 0.7170827829,
    "Mask": "Edge",
    "Method": "EdgeRegressor",
    "Retained": false,
    "SingularValue": 106.9988012717,
    "VarianceExplained": 0.0054722959
  },
  "dropped_67": {
    "CumulativeVarianceExplained": 0.7225288437,
    "Mask": "Edge",
    "Method": "EdgeRegressor",
    "Retained": false,
    "SingularValue": 106.7420083959,
    "VarianceExplained": 0.0054460608
  },
  "dropped_68": {
    "CumulativeVarianceExplained": 0.7279598396,
    "Mask": "Edge",
    "Method": "EdgeRegressor",
    "Retained": false,
    "SingularValue": 106.594270643,
    "VarianceExplained": 0.0054309959
  },
  "dropped_69": {
    "CumulativeVarianceExplained": 0.7333725373,
    "Mask": "Edge",
    "Method": "EdgeRegressor",
    "Retained": false,
    "SingularValue": 106.4145499863,
    "VarianceExplained": 0.0054126977
  },
  "dropped_7": {
    "CumulativeVarianceExplained": 0.363440101,
    "Mask": "Edge",
    "Method": "EdgeRegressor",
    "Retained": false,
    "SingularValue": 118.9212591269,
    "VarianceExplained": 0.0067597517
  },
  "dropped_70": {
    "CumulativeVarianceExplained": 0.7387831125,
    "Mask": "Edge",
    "Method": "EdgeRegressor",
    "Retained": false,
    "SingularValue": 106.3936830068,
    "VarianceExplained": 0.0054105752
  },
  "dropped_71": {
    "CumulativeVarianceExplained": 0.7441694401,
    "Mask": "Edge",
    "Method": "EdgeRegressor",
    "Retained": false,
    "SingularValue": 106.1550130143,
    "VarianceExplained": 0.0053863276
  },
  "dropped_72": {
    "CumulativeVarianceExplained": 0.7495283094,
    "Mask": "Edge",
    "Method": "EdgeRegressor",
    "Retained": false,
    "SingularValue": 105.8840901773,
    "VarianceExplained": 0.0053588693
  },
  "dropped_73": {
    "CumulativeVarianceExplained": 0.7548815115,
    "Mask": "Edge",
    "Method": "EdgeRegressor",
    "Retained": false,
    "SingularValue": 105.8280870729,
    "VarianceExplained": 0.0053532021
  },
  "dropped_74": {
    "CumulativeVarianceExplained": 0.7602188421,
    "Mask": "Edge",
    "Method": "EdgeRegressor",
    "Retained": false,
    "SingularValue": 105.6710878526,
    "VarianceExplained": 0.0053373306
  },
  "dropped_75": {
    "CumulativeVarianceExplained": 0.7655501063,
    "Mask": "Edge",
    "Method": "EdgeRegressor",
    "Retained": false,
    "SingularValue": 105.6110184373,
    "VarianceExplained": 0.0053312643
  },
  "dropped_76": {
    "CumulativeVarianceExplained": 0.7708749432,
    "Mask": "Edge",
    "Method": "EdgeRegressor",
    "Retained": false,
    "SingularValue": 105.5473368211,
    "VarianceExplained": 0.0053248369
  },
  "dropped_77": {
    "CumulativeVarianceExplained": 0.7761857075,
    "Mask": "Edge",
    "Method": "EdgeRegressor",
    "Retained": false,
    "SingularValue": 105.4077731178,
    "VarianceExplained": 0.0053107643
  },
  "dropped_78": {
    "CumulativeVarianceExplained": 0.7814647904,
    "Mask": "Edge",
    "Method": "EdgeRegressor",
    "Retained": false,
    "SingularValue": 105.0928980132,
    "VarianceExplained": 0.0052790829
  },
  "dropped_79": {
    "CumulativeVarianceExplained": 0.7867370541,
    "Mask": "Edge",
    "Method": "EdgeRegressor",
    "Retained": false,
    "SingularValue": 105.0249995753,
    "VarianceExplained": 0.0052722637
  },
  "dropped_8": {
    "CumulativeVarianceExplained": 0.3701429668,
    "Mask": "Edge",
    "Method": "EdgeRegressor",
    "Retained": false,
    "SingularValue": 118.4198173021,
    "VarianceExplained": 0.0067028658
  },
  "dropped_80": {
    "CumulativeVarianceExplained": 0.7919972079,
    "Mask": "Edge",
    "Method": "EdgeRegressor",
    "Retained": false,
    "SingularValue": 104.9043131881,
    "VarianceExplained": 0.0052601537
  },
  "dropped_81": {
    "CumulativeVarianceExplained": 0.7972479939,
    "Mask": "Edge",
    "Method": "EdgeRegressor",
    "Retained": false,
    "SingularValue": 104.8108609649,
    "VarianceExplained": 0.0052507861
  },
  "dropped_82": {
    "CumulativeVarianceExplained": 0.8024767011,
    "Mask": "Edge",
    "Method": "EdgeRegressor",
    "Retained": false,
    "SingularValue": 104.5902700095,
    "VarianceExplained": 0.0052287071
  },
  "dropped_83": {
    "CumulativeVarianceExplained": 0.8076936382,
    "Mask": "Edge",
    "Method": "EdgeRegressor",
    "Retained": false,
    "SingularValue": 104.4724858976,
    "VarianceExplained": 0.0052169372
  },
  "dropped_84": {
    "CumulativeVarianceExplained": 0.8128911373,
    "Mask": "Edge",
    "Method": "EdgeRegressor",
    "Retained": false,
    "SingularValue": 104.2776744204,
    "VarianceExplained": 0.0051974991
  },
  "dropped_85": {
    "CumulativeVarianceExplained": 0.8180727821,
    "Mask": "Edge",
    "Method": "EdgeRegressor",
    "Retained": false,
    "SingularValue": 104.1185096139,
    "VarianceExplained": 0.0051816447
  },
  "dropped_86": {
    "CumulativeVarianceExplained": 0.8232418849,
    "Mask": "Edge",
    "Method": "EdgeRegressor",
    "Retained": false,
    "SingularValue": 103.992426314,
    "VarianceExplained": 0.0051691028
  },
  "dropped_87": {
    "CumulativeVarianceExplained": 0.8283826813,
    "Mask": "Edge",
    "Method": "EdgeRegressor",
    "Retained": false,
    "SingularValue": 103.7073001273,
    "VarianceExplained": 0.0051407964
  },
  "dropped_88": {
    "CumulativeVarianceExplained": 0.8335055903,
    "Mask": "Edge",
    "Method": "EdgeRegressor",
    "Retained": false,
    "SingularValue": 103.5267187758,
    "VarianceExplained": 0.0051229091
  },
  "dropped_89": {
    "CumulativeVarianceExplained": 0.8386253194,
    "Mask": "Edge",
    "Method": "EdgeRegressor",
    "Retained": false,
    "SingularValue": 103.4945818583,
    "VarianceExplained": 0.005119729
  },
  "dropped_9": {
    "CumulativeVarianceExplained": 0.3768079612,
    "Mask": "Edge",
    "Method": "EdgeRegressor",
    "Retained": false,
    "SingularValue": 118.08480576,
    "VarianceExplained": 0.0066649944
  },
  "dropped_90": {
    "CumulativeVarianceExplained": 0.8437433554,
    "Mask": "Edge",
    "Method": "EdgeRegressor",
    "Retained": false,
    "SingularValue": 103.477468051,
    "VarianceExplained": 0.005118036
  },
  "dropped_91": {
    "CumulativeVarianceExplained": 0.8488305582,
    "Mask": "Edge",
    "Method": "EdgeRegressor",
    "Retained": false,
    "SingularValue": 103.165301413,
    "VarianceExplained": 0.0050872028
  },
  "dropped_92": {
    "CumulativeVarianceExplained": 0.8538977717,
    "Mask": "Edge",
    "Method": "EdgeRegressor",
    "Retained": false,
    "SingularValue": 102.9624168243,
    "VarianceExplained": 0.0050672135
  },
  "dropped_93": {
    "CumulativeVarianceExplained": 0.858948872,
    "Mask": "Edge",
    "Method": "EdgeRegressor",
    "Retained": false,
    "SingularValue": 102.7985811648,
    "VarianceExplained": 0.0050511003
  },
  "dropped_94": {
    "CumulativeVarianceExplained": 0.8639914861,
    "Mask": "Edge",
    "Method": "EdgeRegressor",
    "Retained": false,
    "SingularValue": 102.7121913569,
    "VarianceExplained": 0.0050426141
  },
  "dropped_95": {
    "CumulativeVarianceExplained": 0.869009037,
    "Mask": "Edge",
    "Method": "EdgeRegressor",
    "Retained": false,
    "SingularValue": 102.4566188001,
    "VarianceExplained": 0.0050175509
  },
  "dropped_96": {
    "CumulativeVarianceExplained": 0.8740088426,
    "Mask": "Edge",
    "Method": "EdgeRegressor",
    "Retained": false,
    "SingularValue": 102.2752820837,
    "VarianceExplained": 0.0049998056
  },
  "dropped_97": {
    "CumulativeVarianceExplained": 0.8789948794,
    "Mask": "Edge",
    "Method": "EdgeRegressor",
    "Retained": false,
    "SingularValue": 102.134358734,
    "VarianceExplained": 0.0049860368
  },
  "dropped_98": {
    "CumulativeVarianceExplained": 0.8839772895,
    "Mask": "Edge",
    "Method": "EdgeRegressor",
    "Retained": false,
    "SingularValue": 102.0972066255,
    "VarianceExplained": 0.0049824101
  },
  "dropped_99": {
    "CumulativeVarianceExplained": 0.8889457781,
    "Mask": "Edge",
    "Method": "EdgeRegressor",
    "Retained": false,
    "SingularValue": 101.9544704887,
    "VarianceExplained": 0.0049684886
  },
  "edge_comp_00": {
    "CumulativeVarianceExplained": 0.0769605522,
    "Mask": "Edge",
    "Method": "EdgeRegressor",
    "Retained": true,
    "SingularValue": 401.2621664495,
    "VarianceExplained": 0.0769605522
  },
  "edge_comp_01": {
    "CumulativeVarianceExplained": 0.0964944813,
    "Mask": "Edge",
    "Method": "EdgeRegressor",
    "Retained": true,
    "SingularValue": 202.1570676182,
    "VarianceExplained": 0.0195339291
  },
  "edge_comp_02": {
    "CumulativeVarianceExplained": 0.1142750184,
    "Mask": "Edge",
    "Method": "EdgeRegressor",
    "Retained": true,
    "SingularValue": 192.8708363401,
    "VarianceExplained": 0.0177805371
  },
  "edge_comp_03": {
    "CumulativeVarianceExplained": 0.1305859591,
    "Mask": "Edge",
    "Method": "EdgeRegressor",
    "Retained": true,
    "SingularValue": 184.7283836845,
    "VarianceExplained": 0.0163109407
  },
  "edge_comp_04": {
    "CumulativeVarianceExplained": 0.1460081915,
    "Mask": "Edge",
    "Method": "EdgeRegressor",
    "Retained": true,
    "SingularValue": 179.6253995332,
    "VarianceExplained": 0.0154222324
  },
  "edge_comp_05": {
    "CumulativeVarianceExplained": 0.1582046157,
    "Mask": "Edge",
    "Method": "EdgeRegressor",
    "Retained": true,
    "SingularValue": 159.7387885679,
    "VarianceExplained": 0.0121964242
  },
  "edge_comp_06": {
    "CumulativeVarianceExplained": 0.168800002,
    "Mask": "Edge",
    "Method": "EdgeRegressor",
    "Retained": true,
    "SingularValue": 148.8855409605,
    "VarianceExplained": 0.0105953863
  },
  "edge_comp_07": {
    "CumulativeVarianceExplained": 0.1790848442,
    "Mask": "Edge",
    "Method": "EdgeRegressor",
    "Retained": true,
    "SingularValue": 146.687444492,
    "VarianceExplained": 0.0102848422
  },
  "edge_comp_08": {
    "CumulativeVarianceExplained": 0.1887447456,
    "Mask": "Edge",
    "Method": "EdgeRegressor",
    "Retained": true,
    "SingularValue": 142.1610013137,
    "VarianceExplained": 0.0096599014
  },
  "edge_comp_09": {
    "CumulativeVarianceExplained": 0.1979710715,
    "Mask": "Edge",
    "Method": "EdgeRegressor",
    "Retained": true,
    "SingularValue": 138.9339938774,
    "VarianceExplained": 0.0092263259
  },
  "edge_comp_10": {
    "CumulativeVarianceExplained": 0.2070455711,
    "Mask": "Edge",
    "Method": "EdgeRegressor",
    "Retained": true,
    "SingularValue": 137.7861195948,
    "VarianceExplained": 0.0090744996
  },
  "edge_comp_11": {
    "CumulativeVarianceExplained": 0.2155415599,
    "Mask": "Edge",
    "Method": "EdgeRegressor",
    "Retained": true,
    "SingularValue": 133.321776458,
    "VarianceExplained": 0.0084959888
  },
  "edge_comp_12": {
    "CumulativeVarianceExplained": 0.2239774919,
    "Mask": "Edge",
    "Method": "EdgeRegressor",
    "Retained": true,
    "SingularValue": 132.8497251973,
    "VarianceExplained": 0.008435932
  },
  "edge_comp_13": {
    "CumulativeVarianceExplained": 0.23224069,
    "Mask": "Edge",
    "Method": "EdgeRegressor",
    "Retained": true,
    "SingularValue": 131.4825774677,
    "VarianceExplained": 0.0082631981
  },
  "edge_comp_14": {
    "CumulativeVarianceExplained": 0.2403802881,
    "Mask": "Edge",
    "Method": "EdgeRegressor",
    "Retained": true,
    "SingularValue": 130.495521291,
    "VarianceExplained": 0.0081395981
  },
  "edge_comp_15": {
    "CumulativeVarianceExplained": 0.2482940554,
    "Mask": "Edge",
    "Method": "EdgeRegressor",
    "Retained": true,
    "SingularValue": 128.6725070506,
    "VarianceExplained": 0.0079137673
  },
  "edge_comp_16": {
    "CumulativeVarianceExplained": 0.2560884723,
    "Mask": "Edge",
    "Method": "EdgeRegressor",
    "Retained": true,
    "SingularValue": 127.6985434395,
    "VarianceExplained": 0.007794417
  },
  "edge_comp_17": {
    "CumulativeVarianceExplained": 0.263827388,
    "Mask": "Edge",
    "Method": "EdgeRegressor",
    "Retained": true,
    "SingularValue": 127.2430832166,
    "VarianceExplained": 0.0077389157
  },
  "edge_comp_18": {
    "CumulativeVarianceExplained": 0.2714808318,
    "Mask": "Edge",
    "Method": "EdgeRegressor",
    "Retained": true,
    "SingularValue": 126.5384681676,
    "VarianceExplained": 0.0076534437
  },
  "edge_comp_19": {
    "CumulativeVarianceExplained": 0.2790260452,
    "Mask": "Edge",
    "Method": "EdgeRegressor",
    "Retained": true,
    "SingularValue": 125.6405680345,
    "VarianceExplained": 0.0075452135
  },
  "edge_comp_20": {
    "CumulativeVarianceExplained": 0.2865499013,
    "Mask": "Edge",
    "Method": "EdgeRegressor",
    "Retained": true,
    "SingularValue": 125.462624113,
    "VarianceExplained": 0.0075238561
  },
  "edge_comp_21": {
    "CumulativeVarianceExplained": 0.2939213879,
    "Mask": "Edge",
    "Method": "EdgeRegressor",
    "Retained": true,
    "SingularValue": 124.1857213107,
    "VarianceExplained": 0.0073714865
  },
  "edge_comp_22": {
    "CumulativeVarianceExplained": 0.3011887038,
    "Mask": "Edge",
    "Method": "EdgeRegressor",
    "Retained": true,
    "SingularValue": 123.3051298313,
    "VarianceExplained": 0.0072673159
  },
  "edge_comp_23": {
    "CumulativeVarianceExplained": 0.3083757415,
    "Mask": "Edge",
    "Method": "EdgeRegressor",
    "Retained": true,
    "SingularValue": 122.6221955677,
    "VarianceExplained": 0.0071870377
  },
  "framewise_displacement": {
    "Units": "mm"
  },
  "rot_x": {
    "Description": "Rotation about left-right axis. Also known as \"pitch\".",
    "Units": "rad"
  },
  "rot_y": {
    "Description": "Rotation about anterior-posterior axis. Also known as \"roll\".",
    "Units": "rad"
  },
  "rot_z": {
    "Description": "Rotation about superior-inferior axis. Also known as \"yaw\".",
    "Units": "rad"
  },
  "t_comp_cor_00": {
    "CumulativeVarianceExplained": 0.2181708409,
    "Method": "tCompCor",
    "Retained": true,
    "SingularValue": 188.2820851761,
    "VarianceExplained": 0.2181708409
  },
  "t_comp_cor_01": {
    "CumulativeVarianceExplained": 0.3074871443,
    "Method": "tCompCor",
    "Retained": true,
    "SingularValue": 120.4691973083,
    "VarianceExplained": 0.0893163034
  },
  "t_comp_cor_02": {
    "CumulativeVarianceExplained": 0.3870620039,
    "Method": "tCompCor",
    "Retained": true,
    "SingularValue": 113.7099810402,
    "VarianceExplained": 0.0795748596
  },
  "t_comp_cor_03": {
    "CumulativeVarianceExplained": 0.4447668542,
    "Method": "tCompCor",
    "Retained": true,
    "SingularValue": 96.8315326671,
    "VarianceExplained": 0.0577048503
  },
  "t_comp_cor_04": {
    "CumulativeVarianceExplained": 0.4765962914,
    "Method": "tCompCor",
    "Retained": true,
    "SingularValue": 71.9159341499,
    "VarianceExplained": 0.0318294372
  },
  "t_comp_cor_05": {
    "CumulativeVarianceExplained": 0.5038106829,
    "Method": "tCompCor",
    "Retained": true,
    "SingularValue": 66.4982109177,
    "VarianceExplained": 0.0272143916
  },
  "trans_x": {
    "Description": "Translation along left-right axis.",
    "Units": "mm"
  },
  "trans_y": {
    "Description": "Translation along anterior-posterior axis.",
    "Units": "mm"
  },
  "trans_z": {
    "Description": "Translation along superior-inferior axis.",
    "Units": "mm"
  },
  "w_comp_cor_00": {
    "CumulativeVarianceExplained": 0.0285607382,
    "Mask": "WM",
    "Method": "aCompCor",
    "Retained": true,
    "SingularValue": 93.5285138531,
    "VarianceExplained": 0.0285607382
  },
  "w_comp_cor_01": {
    "CumulativeVarianceExplained": 0.0410195471,
    "Mask": "WM",
    "Method": "aCompCor",
    "Retained": true,
    "SingularValue": 61.7728418016,
    "VarianceExplained": 0.0124588089
  },
  "w_comp_cor_02": {
    "CumulativeVarianceExplained": 0.0527758528,
    "Mask": "WM",
    "Method": "aCompCor",
    "Retained": true,
    "SingularValue": 60.0060106786,
    "VarianceExplained": 0.0117563057
  },
  "w_comp_cor_03": {
    "CumulativeVarianceExplained": 0.0639738291,
    "Mask": "WM",
    "Method": "aCompCor",
    "Retained": true,
    "SingularValue": 58.5637785811,
    "VarianceExplained": 0.0111979762
  },
  "w_comp_cor_04": {
    "CumulativeVarianceExplained": 0.0747301806,
    "Mask": "WM",
    "Method": "aCompCor",
    "Retained": true,
    "SingularValue": 57.3973460841,
    "VarianceExplained": 0.0107563515
  },
  "w_comp_cor_05": {
    "CumulativeVarianceExplained": 0.0851917358,
    "Mask": "WM",
    "Method": "aCompCor",
    "Retained": true,
    "SingularValue": 56.6053454161,
    "VarianceExplained": 0.0104615552
  },
  "w_comp_cor_06": {
    "CumulativeVarianceExplained": 0.0954822169,
    "Mask": "WM",
    "Method": "aCompCor",
    "Retained": true,
    "SingularValue": 56.1406140241,
    "VarianceExplained": 0.0102904811
  },
  "w_comp_cor_07": {
    "CumulativeVarianceExplained": 0.1056305454,
    "Mask": "WM",
    "Method": "aCompCor",
    "Retained": true,
    "SingularValue": 55.7515028247,
    "VarianceExplained": 0.0101483285
  },
  "w_comp_cor_08": {
    "CumulativeVarianceExplained": 0.1155767345,
    "Mask": "WM",
    "Method": "aCompCor",
    "Retained": true,
    "SingularValue": 55.1934669703,
    "VarianceExplained": 0.0099461891
  },
  "w_comp_cor_09": {
    "CumulativeVarianceExplained": 0.1254877519,
    "Mask": "WM",
    "Method": "aCompCor",
    "Retained": true,
    "SingularValue": 55.0957931407,
    "VarianceExplained": 0.0099110174
  },
  "w_comp_cor_10": {
    "CumulativeVarianceExplained": 0.1352850348,
    "Mask": "WM",
    "Method": "aCompCor",
    "Retained": true,
    "SingularValue": 54.7787531307,
    "VarianceExplained": 0.0097972829
  },
  "w_comp_cor_11": {
    "CumulativeVarianceExplained": 0.1449774747,
    "Mask": "WM",
    "Method": "aCompCor",
    "Retained": true,
    "SingularValue": 54.484864743,
    "VarianceExplained": 0.0096924399
  },
  "w_comp_cor_12": {
    "CumulativeVarianceExplained": 0.1545534709,
    "Mask": "WM",
    "Method": "aCompCor",
    "Retained": true,
    "SingularValue": 54.1565889308,
    "VarianceExplained": 0.0095759962
  },
  "w_comp_cor_13": {
    "CumulativeVarianceExplained": 0.1640534828,
    "Mask": "WM",
    "Method": "aCompCor",
    "Retained": true,
    "SingularValue": 53.9412982551,
    "VarianceExplained": 0.0095000119
  },
  "w_comp_cor_14": {
    "CumulativeVarianceExplained": 0.1734888091,
    "Mask": "WM",
    "Method": "aCompCor",
    "Retained": true,
    "SingularValue": 53.7573411614,
    "VarianceExplained": 0.0094353263
  },
  "w_comp_cor_15": {
    "CumulativeVarianceExplained": 0.1828890264,
    "Mask": "WM",
    "Method": "aCompCor",
    "Retained": true,
    "SingularValue": 53.6572320767,
    "VarianceExplained": 0.0094002173
  },
  "w_comp_cor_16": {
    "CumulativeVarianceExplained": 0.1922556237,
    "Mask": "WM",
    "Method": "aCompCor",
    "Retained": true,
    "SingularValue": 53.5611932652,
    "VarianceExplained": 0.0093665973
  },
  "w_comp_cor_17": {
    "CumulativeVarianceExplained": 0.2014398524,
    "Mask": "WM",
    "Method": "aCompCor",
    "Retained": true,
    "SingularValue": 53.0372092243,
    "VarianceExplained": 0.0091842287
  },
  "w_comp_cor_18": {
    "CumulativeVarianceExplained": 0.2105596347,
    "Mask": "WM",
    "Method": "aCompCor",
    "Retained": true,
    "SingularValue": 52.8507987392,
    "VarianceExplained": 0.0091197823
  },
  "w_comp_cor_19": {
    "CumulativeVarianceExplained": 0.2196138494,
    "Mask": "WM",
    "Method": "aCompCor",
    "Retained": true,
    "SingularValue": 52.6604679174,
    "VarianceExplained": 0.0090542147
  },
  "w_comp_cor_20": {
    "CumulativeVarianceExplained": 0.2286109755,
    "Mask": "WM",
    "Method": "aCompCor",
    "Retained": true,
    "SingularValue": 52.4941880468,
    "VarianceExplained": 0.0089971261
  },
  "w_comp_cor_21": {
    "CumulativeVarianceExplained": 0.2375279325,
    "Mask": "WM",
    "Method": "aCompCor",
    "Retained": true,
    "SingularValue": 52.259789467,
    "VarianceExplained": 0.008916957
  },
  "w_comp_cor_22": {
    "CumulativeVarianceExplained": 0.246406402,
    "Mask": "WM",
    "Method": "aCompCor",
    "Retained": true,
    "SingularValue": 52.1468851605,
    "VarianceExplained": 0.0088784695
  },
  "w_comp_cor_23": {
    "CumulativeVarianceExplained": 0.25522351,
    "Mask": "WM",
    "Method": "aCompCor",
    "Retained": true,
    "SingularValue": 51.9663721677,
    "VarianceExplained": 0.008817108
  },
  "w_comp_cor_24": {
    "CumulativeVarianceExplained": 0.2639642518,
    "Mask": "WM",
    "Method": "aCompCor",
    "Retained": true,
    "SingularValue": 51.7408386687,
    "VarianceExplained": 0.0087407418
  },
  "w_comp_cor_25": {
    "CumulativeVarianceExplained": 0.272691786,
    "Mask": "WM",
    "Method": "aCompCor",
    "Retained": true,
    "SingularValue": 51.7017330008,
    "VarianceExplained": 0.0087275343
  },
  "w_comp_cor_26": {
    "CumulativeVarianceExplained": 0.2813920478,
    "Mask": "WM",
    "Method": "aCompCor",
    "Retained": true,
    "SingularValue": 51.6208889111,
    "VarianceExplained": 0.0087002618
  },
  "w_comp_cor_27": {
    "CumulativeVarianceExplained": 0.2900023806,
    "Mask": "WM",
    "Method": "aCompCor",
    "Retained": true,
    "SingularValue": 51.3534101828,
    "VarianceExplained": 0.0086103328
  },
  "w_comp_cor_28": {
    "CumulativeVarianceExplained": 0.2985958078,
    "Mask": "WM",
    "Method": "aCompCor",
    "Retained": true,
    "SingularValue": 51.3029715714,
    "VarianceExplained": 0.0085934272
  },
  "w_comp_cor_29": {
    "CumulativeVarianceExplained": 0.3070881404,
    "Mask": "WM",
    "Method": "aCompCor",
    "Retained": true,
    "SingularValue": 51.0003099285,
    "VarianceExplained": 0.0084923325
  },
  "w_comp_cor_30": {
    "CumulativeVarianceExplained": 0.3155319816,
    "Mask": "WM",
    "Method": "aCompCor",
    "Retained": true,
    "SingularValue": 50.8544951922,
    "VarianceExplained": 0.0084438412
  },
  "w_comp_cor_31": {
    "CumulativeVarianceExplained": 0.3239295912,
    "Mask": "WM",
    "Method": "aCompCor",
    "Retained": true,
    "SingularValue": 50.7150853657,
    "VarianceExplained": 0.0083976097
  },
  "w_comp_cor_32": {
    "CumulativeVarianceExplained": 0.3322827485,
    "Mask": "WM",
    "Method": "aCompCor",
    "Retained": true,
    "SingularValue": 50.5806781013,
    "VarianceExplained": 0.0083531572
  },
  "w_comp_cor_33": {
    "CumulativeVarianceExplained": 0.3405398117,
    "Mask": "WM",
    "Method": "aCompCor",
    "Retained": true,
    "SingularValue": 50.2888987578,
    "VarianceExplained": 0.0082570633
  },
  "w_comp_cor_34": {
    "CumulativeVarianceExplained": 0.3487311192,
    "Mask": "WM",
    "Method": "aCompCor",
    "Retained": true,
    "SingularValue": 50.0882584403,
    "VarianceExplained": 0.0081913074
  },
  "w_comp_cor_35": {
    "CumulativeVarianceExplained": 0.3568640809,
    "Mask": "WM",
    "Method": "aCompCor",
    "Retained": true,
    "SingularValue": 49.909553425,
    "VarianceExplained": 0.0081329617
  },
  "w_comp_cor_36": {
    "CumulativeVarianceExplained": 0.3649677687,
    "Mask": "WM",
    "Method": "aCompCor",
    "Retained": true,
    "SingularValue": 49.819649597,
    "VarianceExplained": 0.0081036878
  },
  "w_comp_cor_37": {
    "CumulativeVarianceExplained": 0.3730169184,
    "Mask": "WM",
    "Method": "aCompCor",
    "Retained": true,
    "SingularValue": 49.6517228303,
    "VarianceExplained": 0.0080491497
  },
  "w_comp_cor_38": {
    "CumulativeVarianceExplained": 0.3809801936,
    "Mask": "WM",
    "Method": "aCompCor",
    "Retained": true,
    "SingularValue": 49.3861512405,
    "VarianceExplained": 0.0079632752
  },
  "w_comp_cor_39": {
    "CumulativeVarianceExplained": 0.3888613268,
    "Mask": "WM",
    "Method": "aCompCor",
    "Retained": true,
    "SingularValue": 49.1307794211,
    "VarianceExplained": 0.0078811332
  },
  "w_comp_cor_40": {
    "CumulativeVarianceExplained": 0.3967306771,
    "Mask": "WM",
    "Method": "aCompCor",
    "Retained": true,
    "SingularValue": 49.094038251,
    "VarianceExplained": 0.0078693502
  },
  "w_comp_cor_41": {
    "CumulativeVarianceExplained": 0.404566657,
    "Mask": "WM",
    "Method": "aCompCor",
    "Retained": true,
    "SingularValue": 48.9898350791,
    "VarianceExplained": 0.00783598
  },
  "w_comp_cor_42": {
    "CumulativeVarianceExplained": 0.412373693,
    "Mask": "WM",
    "Method": "aCompCor",
    "Retained": true,
    "SingularValue": 48.8992736208,
    "VarianceExplained": 0.0078070359
  },
  "w_comp_cor_43": {
    "CumulativeVarianceExplained": 0.4201281911,
    "Mask": "WM",
    "Method": "aCompCor",
    "Retained": true,
    "SingularValue": 48.7344611229,
    "VarianceExplained": 0.0077544982
  },
  "w_comp_cor_44": {
    "CumulativeVarianceExplained": 0.4278396471,
    "Mask": "WM",
    "Method": "aCompCor",
    "Retained": true,
    "SingularValue": 48.5990198539,
    "VarianceExplained": 0.007711456
  },
  "w_comp_cor_45": {
    "CumulativeVarianceExplained": 0.4355284595,
    "Mask": "WM",
    "Method": "aCompCor",
    "Retained": true,
    "SingularValue": 48.5276154317,
    "VarianceExplained": 0.0076888124
  },
  "w_comp_cor_46": {
    "CumulativeVarianceExplained": 0.4431432776,
    "Mask": "WM",
    "Method": "aCompCor",
    "Retained": true,
    "SingularValue": 48.2935450739,
    "VarianceExplained": 0.0076148181
  },
  "w_comp_cor_47": {
    "CumulativeVarianceExplained": 0.4507271085,
    "Mask": "WM",
    "Method": "aCompCor",
    "Retained": true,
    "SingularValue": 48.1951835653,
    "VarianceExplained": 0.0075838309
  },
  "w_comp_cor_48": {
    "CumulativeVarianceExplained": 0.4581998234,
    "Mask": "WM",
    "Method": "aCompCor",
    "Retained": true,
    "SingularValue": 47.8408102511,
    "VarianceExplained": 0.0074727149
  },
  "w_comp_cor_49": {
    "CumulativeVarianceExplained": 0.4656576566,
    "Mask": "WM",
    "Method": "aCompCor",
    "Retained": true,
    "SingularValue": 47.7931497574,
    "VarianceExplained": 0.0074578332
  },
  "w_comp_cor_50": {
    "CumulativeVarianceExplained": 0.4730121945,
    "Mask": "WM",
    "Method": "aCompCor",
    "Retained": true,
    "SingularValue": 47.4610142042,
    "VarianceExplained": 0.0073545379
  },
  "w_comp_cor_51": {
    "CumulativeVarianceExplained": 0.4803363829,
    "Mask": "WM",
    "Method": "aCompCor",
    "Retained": true,
    "SingularValue": 47.362985623,
    "VarianceExplained": 0.0073241883
  },
  "w_comp_cor_52": {
    "CumulativeVarianceExplained": 0.4876408617,
    "Mask": "WM",
    "Method": "aCompCor",
    "Retained": true,
    "SingularValue": 47.2992153796,
    "VarianceExplained": 0.0073044788
  },
  "w_comp_cor_53": {
    "CumulativeVarianceExplained": 0.4949204333,
    "Mask": "WM",
    "Method": "aCompCor",
    "Retained": true,
    "SingularValue": 47.2185046528,
    "VarianceExplained": 0.0072795716
  },
  "w_comp_cor_54": {
    "CumulativeVarianceExplained": 0.5021709272,
    "Mask": "WM",
    "Method": "aCompCor",
    "Retained": true,
    "SingularValue": 47.1241050479,
    "VarianceExplained": 0.0072504939
  }
}